giis_signer/__init__.py
giis_signer/cli.py
giis_signer/cryptopro_signer.py
giis_signer/diagnostics.py
giis_signer/xml_signer.py
giis_signer/gui/__init__.py
giis_signer/gui/app.py
giis_signer/gui/certificate_dialog.py
giis_signer/gui/certificate_manager.py
giis_signer/gui/config.py
giis_signer/gui/toast.py
giis_signer-1.0.0.dist-info/licenses/LICENSE
giis_signer-1.0.0.dist-info/METADATA
giis_signer-1.0.0.dist-info/WHEEL
giis_signer-1.0.0.dist-info/entry_points.txt
giis_signer-1.0.0.dist-info/top_level.txt
giis_signer-1.0.0.dist-info/RECORD
