Metadata-Version: 2.4
Name: giis-signer
Version: 1.0.0
Summary: Утилита для подписания XML-документов по стандарту XMLDSig с требованиями ГИИС ДМДК, используя КриптоПро CSP
Author: GIIS Signer Contributors
License: MIT
Project-URL: Homepage, https://github.com/imdeniil/giis-signer
Project-URL: Documentation, https://github.com/imdeniil/giis-signer/blob/master/README.md
Project-URL: Repository, https://github.com/imdeniil/giis-signer
Project-URL: Bug Tracker, https://github.com/imdeniil/giis-signer/issues
Keywords: xml,xmldsig,cryptopro,gost,signature,giis,dmdк,smev,russian-cryptography
Classifier: Development Status :: 5 - Production/Stable
Classifier: Intended Audience :: Developers
Classifier: License :: OSI Approved :: MIT License
Classifier: Operating System :: Microsoft :: Windows
Classifier: Programming Language :: Python :: 3
Classifier: Programming Language :: Python :: 3.8
Classifier: Programming Language :: Python :: 3.9
Classifier: Programming Language :: Python :: 3.10
Classifier: Programming Language :: Python :: 3.11
Classifier: Programming Language :: Python :: 3.12
Classifier: Topic :: Security :: Cryptography
Classifier: Topic :: Software Development :: Libraries :: Python Modules
Requires-Python: >=3.8
License-File: LICENSE
Requires-Dist: pywin32>=305
Requires-Dist: lxml>=4.9.0
Requires-Dist: xmlcanon>=1.0.0
Requires-Dist: smev-transform>=2.0.0
Requires-Dist: customtkinter>=5.2.0
Provides-Extra: dev
Requires-Dist: pytest>=7.0.0; extra == "dev"
Requires-Dist: black>=22.0.0; extra == "dev"
Requires-Dist: flake8>=4.0.0; extra == "dev"
Requires-Dist: mypy>=0.950; extra == "dev"
Dynamic: license-file
